shok/__init__.py
shok/__main__.py
shok/cli.py
shok/main.py
shok/py.typed
shok/data/__init__.py
shok/data/datasets/__init__.py
shok/data/datasets/coco.py
shok/data/datasets/utils.py
shok/patch/__init__.py
shok/patch/module.py
shok/utils/__init__.py
shok/utils/callbacks.py
shok/utils/functions.py
shok/utils/optim.py
shok/utils/transforms.py
shok-0.1.1.dist-info/licenses/LICENSE
shok-0.1.1.dist-info/METADATA
shok-0.1.1.dist-info/WHEEL
shok-0.1.1.dist-info/entry_points.txt
shok-0.1.1.dist-info/top_level.txt
shok-0.1.1.dist-info/RECORD
