Metadata-Version: 2.4
Name: shok
Version: 0.1.1
Author-email: Benjamin Etheredge <benjamin.etheredge@gmail.com>
License: MIT
Project-URL: Bug Tracker, https://github.com/benjamin-etheredge/shok/issues
Project-URL: Changelog, https://github.com/benjamin-etheredge/shok/blob/main/CHANGELOG.md
Project-URL: documentation, https://shok.readthedocs.io
Project-URL: repository, https://github.com/benjamin-etheredge/shok
Classifier: Development Status :: 2 - Pre-Alpha
Classifier: Intended Audience :: Developers
Classifier: Natural Language :: English
Classifier: Operating System :: OS Independent
Classifier: Programming Language :: Python :: 3.9
Classifier: Programming Language :: Python :: 3.10
Classifier: Programming Language :: Python :: 3.11
Classifier: Programming Language :: Python :: 3.12
Classifier: Programming Language :: Python :: 3.13
Classifier: Topic :: Software Development :: Libraries
Requires-Python: >=3.9
License-File: LICENSE
Requires-Dist: faster-coco-eval>=1.6.7
Requires-Dist: fiftyone>=1.7.0
Requires-Dist: icecream>=2.1.5
Requires-Dist: jsonargparse[signatures]>=4.40.0
Requires-Dist: lightning>=2.5.2
Requires-Dist: rich>=10
Requires-Dist: torch>=2.7.1
Requires-Dist: torchmetrics>=1.7.4
Requires-Dist: torchvision>=0.22.1
Requires-Dist: typer<1,>=0.15
Requires-Dist: wandb>=0.21.0
Dynamic: license-file
